cutp/app.py
cutp/utils/gen.py
cutp/utils/ports.py
cutp-0.1.1.dist-info/LICENSE
cutp-0.1.1.dist-info/METADATA
cutp-0.1.1.dist-info/WHEEL
cutp-0.1.1.dist-info/entry_points.txt
cutp-0.1.1.dist-info/RECORD
