Metadata-Version: 2.1
Name: cutp
Version: 0.1.1
Summary: Check that your container's TCP port does not conflict with the port used by your Umbrel.
Author: Henrique Sebastião
Author-email: contato@henriquesebastiao.com
Requires-Python: >=3.12,<4.0
Classifier: Programming Language :: Python :: 3
Classifier: Programming Language :: Python :: 3.12
Requires-Dist: typer (>=0.13.1,<0.14.0)
